asap_o_matic-2.5.2.dist-info/METADATA
asap_o_matic-2.5.2.dist-info/WHEEL
asap_o_matic-2.5.2.dist-info/entry_points.txt
asap_o_matic-2.5.2.dist-info/licenses/LICENSE
asap_o_matic/__main__.py
asap_o_matic/logger.py
asap_o_matic/__init__.py
asap_o_matic/asap_o_matic.abi3.so
asap_o_matic-2.5.2.dist-info/RECORD
