Metadata-Version: 2.3
Name: asap-o-matic
Version: 2.5.2
Classifier: Programming Language :: Python
Classifier: Programming Language :: Python :: Implementation :: CPython
Classifier: Programming Language :: Python :: Implementation :: PyPy
Classifier: Programming Language :: Python :: 3.11
Classifier: Programming Language :: Python :: 3.12
Classifier: Programming Language :: Python :: 3.13
Classifier: Programming Language :: Python :: 3.14
Classifier: Programming Language :: Python :: 3 :: Only
Classifier: Programming Language :: Rust
Classifier: Development Status :: 5 - Production/Stable
Classifier: Environment :: Console
Classifier: Intended Audience :: Science/Research
Classifier: License :: OSI Approved :: GNU General Public License v3 (GPLv3)
Classifier: Topic :: Scientific/Engineering :: Bio-Informatics
Classifier: Typing :: Typed
Classifier: Topic :: Software Development :: Libraries :: Python Modules
Requires-Dist: typer >=0.15.1
Requires-Dist: loguru >=0.7.2
Requires-Dist: multiprocess >=0.70.16
Requires-Dist: rich >=13.9.4
Requires-Dist: fastq >=2.0.4
Requires-Dist: revseq >=1.2.0
Requires-Dist: minifasta >=3.0.3
Requires-Dist: joblib >=1.4.2
Requires-Dist: pysam >=0.23.0
License-File: LICENSE
Summary: Rearrange ASAP-seq antibody reads into something Alevin can recognize and count.
Author-email: Miles Smith <miles-smith@omrf.org>
License: GPL-3.0
Requires-Python: >=3.11
Project-URL: repository, https://github.com/milescsmith/asap_o_matic
Project-URL: homepage, https://github.com/milescsmith/asap_o_matic
